seshatdatasetanalysis/__init__.py
seshatdatasetanalysis/mappings.py
seshatdatasetanalysis/plotting.py
seshatdatasetanalysis/Template.py
seshatdatasetanalysis/TimeSeriesDataset.py
seshatdatasetanalysis/utils.py
seshatdatasetanalysis-0.3.6.dist-info/LICENSE
seshatdatasetanalysis-0.3.6.dist-info/METADATA
seshatdatasetanalysis-0.3.6.dist-info/WHEEL
seshatdatasetanalysis-0.3.6.dist-info/RECORD
