Metadata-Version: 2.3
Name: seshatdatasetanalysis
Version: 0.3.6
Summary: A package for analyzing time series datasets from the Seshat databank.
License: MIT
Author: Matilda Peruzzo
Author-email: matilda.peruzzo@gmail.com
Requires-Python: >=3.10,<4.0
Classifier: License :: OSI Approved :: MIT License
Classifier: Programming Language :: Python :: 3
Classifier: Programming Language :: Python :: 3.10
Classifier: Programming Language :: Python :: 3.11
Classifier: Programming Language :: Python :: 3.12
Classifier: Programming Language :: Python :: 3.13
Requires-Dist: geopandas (>=1.0.0,<2.0.0)
Requires-Dist: matplotlib (>=3.4.3,<4.0.0)
Requires-Dist: numpy (>=1.21.2,<2.0.0)
Requires-Dist: openpyxl (>=3.0.9,<4.0.0)
Requires-Dist: pandas (>=2.1.0,<3.0.0)
Requires-Dist: pyreadr (>=0.4.5,<0.5.0)
Requires-Dist: requests (>=2.0.0,<3.0.0)
Requires-Dist: scikit-learn (>=1.0.1,<2.0.0)
Requires-Dist: scipy (==1.15.3)
Requires-Dist: seaborn (==0.12.2)
Requires-Dist: statsmodels (>=0.13.2,<0.14.0)
Requires-Dist: xlsxwriter (>=3.0.3,<4.0.0)
